[
  {
    "id": "hale-manavi",
    "name": "حال معنوی",
    "company": "شرکت طلوع نجم",
    "from": "تابستان ۱۴۰۴",
    "to": "حال حاضر",
    "description": "«حال معنوی» دومین پروژه‌ای هست که من هم طراحی UI/UX و هم کدنویسی سمت فرانت‌اند اون رو به عهده دارم."
  },
  {
    "id": "auriogold",
    "name": "اوریوگلد",
    "company": "شرکت طلوع نجم",
    "from": "بهار ۱۴۰۴",
    "to": "تابستان ۱۴۰۴",
    "description": "اوریوگلد در واقع نسخه تمیزتر، زیبا،‌ سریع‌تر و مورد اطمینان‌تر «وی‌گلد» بود که ساخته شد و برای معاملات طلا و امثالهم استفاده می‌شد."
  },
  {
    "id": "tims",
    "name": "سیستم TIMS",
    "company": "شرکت طلوع نجم",
    "from": "؟؟؟",
    "to": "؟؟؟",
    "description": "اولین پروژه من که با تایپ‌اسکریپت نوشته شد و من تاثیر تایپ‌اسکریپت رو در پروژه‌های واقعی دیدم..."
  },
  {
    "id": "vgold",
    "name": "وی‌گلد",
    "company": "شرکت طلوع نجم",
    "from": "؟؟؟",
    "to": "؟؟؟",
    "description": "«وی‌گلد» اولین پروژه‌ای بود که من هم طراحی UI/UX و هم کدنویسی سمت فرانت‌اند اون رو به عهده گرفتم."
  }
]
